matrixscreener/__init__.py
matrixscreener/cam.py
matrixscreener/experiment.py
matrixscreener/utils.py
matrixscreener-0.6.1.dist-info/DESCRIPTION.rst
matrixscreener-0.6.1.dist-info/METADATA
matrixscreener-0.6.1.dist-info/RECORD
matrixscreener-0.6.1.dist-info/WHEEL
matrixscreener-0.6.1.dist-info/metadata.json
matrixscreener-0.6.1.dist-info/top_level.txt
