Metadata-Version: 2.0
Name: matrixscreener
Version: 0.6.1
Summary: Python API for Leica LAS AF MatrixScreener
Home-page: https://github.com/arve0/matrixscreener
Author: Arve Seljebu
Author-email: arve.seljebu@gmail.com
License: MIT
Platform: UNKNOWN
Requires-Dist: Pillow
Requires-Dist: fijibin
Requires-Dist: pydebug
